
pub mod opcode {

    #[allow(dead_code)]
    pub enum Opcode {
    //    MNEMONIC,
        Aaload          = 0x32,
        Aastore         = 0x53,
        AconstNull      = 0x01,
        Aload           = 0x19,
        Aload0          = 0x2a,
        Aload1          = 0x2b,
        Aload2          = 0x2c,
        Aload3          = 0x2d,
        Anewarray       = 0xbd,
        Areturn         = 0xb0,
        Arraylength     = 0xbe,
        Astore          = 0x3a,
        Astore0         = 0x4b,
        Astore1         = 0x4c,
        Astore2         = 0x4d,
        Astore3         = 0x4e,
        Athrow          = 0xbf,
        Baload          = 0x33,
        Bastore         = 0x54,
        Bipush          = 0x10,
        Caload          = 0x34,
        Castore         = 0x55,
        Checkcast       = 0xc0,
        D2f             = 0x90,
        D2i             = 0x8e,
        D2l             = 0x8f,
        Dadd            = 0x63,
        Daload          = 0x31,
        Dastore         = 0x52,
        Dcmpg           = 0x98,
        Dcmpl           = 0x97,
        Dconst0         = 0x0e,
        Dconst1         = 0x0f,
        Ddiv            = 0x6f,
        Dload           = 0x18,
        Dload0          = 0x26,
        Dload1          = 0x27,
        Dload2          = 0x28,
        Dload3          = 0x29,
        Dmul            = 0x6b,
        Dneg            = 0x77,
        Drem            = 0x73,
        Dreturn         = 0xaf,
        Dstore          = 0x39,
        Dstore0         = 0x47,
        Dstore1         = 0x48,
        Dstore2         = 0x49,
        Dstore3         = 0x4a,
        Dsub            = 0x67,
        Dup             = 0x59,
        DupX1           = 0x5a,
        DupX2           = 0x5b,
        Dup2            = 0x5c,
        Dup2X1          = 0x5d,
        Dup2X2          = 0x5e,
        F2d             = 0x8d,
        F2i             = 0x8b,
        F2l             = 0x8c,
        Fadd            = 0x62,
        Faload          = 0x30,
        Fastore         = 0x51,
        Fcmpg           = 0x96,
        Fcmpl           = 0x95,
        Fconst0         = 0x0b,
        Fconst1         = 0x0c,
        Fconst2         = 0x0d,
        Fdiv            = 0x6e,
        Fload           = 0x17,
        Fload0          = 0x22,
        Fload1          = 0x23,
        Fload2          = 0x24,
        Fload3          = 0x25,
        Fmul            = 0x6a,
        Fneg            = 0x76,
        Frem            = 0x72,
        Freturn         = 0xae,
        Fstore          = 0x38,
        Fstore0         = 0x43,
        Fstore1         = 0x44,
        Fstore2         = 0x45,
        Fstore3         = 0x46,
        Fsub            = 0x66,
        Getfield        = 0xb4,
        Getstatic       = 0xb2,
        Goto            = 0xa7,
        GotoW           = 0xc8,
        I2b             = 0x91,
        I2c             = 0x92,
        I2d             = 0x87,
        I2f             = 0x86,
        I2l             = 0x85,
        I2s             = 0x93,
        Iadd            = 0x60,
        Iaload          = 0x2e,
        Iand            = 0x7e,
        Iastore         = 0x4f,
        IconstM1        = 0x02,
        Iconst0         = 0x03,
        Iconst1         = 0x04,
        Iconst2         = 0x05,
        Iconst3         = 0x06,
        Iconst4         = 0x07,
        Iconst5         = 0x08,
        Idiv            = 0x6c,
        IfAcmpeq        = 0xa5,
        IfAcmpne        = 0xa6,
        IfIcmpeq        = 0x9f,
        IfIcmpne        = 0xa0,
        IfIcmplt        = 0xa1,
        IfIcmpge        = 0xa2,
        IfIcmpgt        = 0xa3,
        IfIcmple        = 0xa4,
        Ifeq            = 0x99,
        Ifne            = 0x9a,
        Iflt            = 0x9b,
        Ifge            = 0x9c,
        Ifgt            = 0x9d,
        Ifle            = 0x9e,
        Ifnonnull       = 0xc7,
        Iinc            = 0x84,
        Iload           = 0x15,
        Iload0          = 0x1a,
        Iload1          = 0x1b,
        Iload2          = 0x1c,
        Iload3          = 0x1d,
        Imul            = 0x68,
        Ineg            = 0x74,
        Instanceof      = 0xc1,
        Invokedynamic   = 0xba,
        Invokeinterface = 0xb9,
        Invokespecial   = 0xb7,
        Invokestatic    = 0xb8,
        Invokevirtual   = 0xb6,
        Ior             = 0x80,
        Irem            = 0x70,
        Ireturn         = 0xac,
        Ishl            = 0x78,
        Ishr            = 0x7a,
        Istore          = 0x36,
        Istore0         = 0x3b,
        Istore1         = 0x3c,
        Istore2         = 0x3d,
        Istore3         = 0x3e,
        Isub            = 0x64,
        Iushr           = 0x7c,
        Ixor            = 0x82,
        Jsr             = 0xa8,
        JsrW            = 0xc9,
        L2d             = 0x8a,
        L2f             = 0x89,
        L2i             = 0x88,
        Ladd            = 0x61,
        Laload          = 0x2f,
        Land            = 0x7f,
        Lastore         = 0x50,
        Lcmp            = 0x94,
        Lconst0         = 0x09,
        Lconst1         = 0x0a,
        Ldc             = 0x12,
        LdcW            = 0x13,
        Ldc2W           = 0x14,
        Ldiv            = 0x6d,
        Lload           = 0x16,
        Lload0          = 0x1e,
        Lload1          = 0x1f,
        Lload2          = 0x20,
        Lload3          = 0x21,
        Lmul            = 0x69,
        Lneg            = 0x75,
        Lookupswitch    = 0xab,
        Lor             = 0x81,
        Lrem            = 0x71,
        Lreturn         = 0xad,
        Lshl            = 0x79,
        Lshr            = 0x7b,
        Lstore          = 0x37,
        Lstore0         = 0x3f,
        Lstore1         = 0x40,
        Lstore2         = 0x41,
        Lstore3         = 0x42,
        Lsub            = 0x65,
        Lushr           = 0x7d,
        Lxor            = 0x83,
        Monitorenter    = 0xc2,
        Monitorexit     = 0xc3,
        Multianewarray  = 0xc5,
        New             = 0xbb,
        Newarray        = 0xbc,
        Nop             = 0x00,
        Pop             = 0x57,
        Pop2            = 0x58,
        Putfield        = 0xb5,
        Putstatic       = 0xb3,
        Ret             = 0xa9,
        Return          = 0xb1,
        Saload          = 0x35,
        Sastore         = 0x56,
        Sipush          = 0x11,
        Swap            = 0x5f,
        Tableswitch     = 0xaa,
        Wide            = 0xc4
    }

    pub fn from_u8(byte: u8) -> Option<Opcode> {
        match byte {
            0x31 => Some(Opcode::Aaload),
            0x53 => Some(Opcode::Aastore),
            0x01 => Some(Opcode::AconstNull),
            0x19 => Some(Opcode::Aload),
            0x2a => Some(Opcode::Aload1),
            0x2b => Some(Opcode::Aload1),
            0x2c => Some(Opcode::Aload2),
            0x2d => Some(Opcode::Aload3),
            0xbd => Some(Opcode::Anewarray),
            0xb0 => Some(Opcode::Areturn),
            0xbe => Some(Opcode::Arraylength),
            0x3a => Some(Opcode::Astore),
            0x4b => Some(Opcode::Astore0),
            0x4c => Some(Opcode::Astore1),
            0x4d => Some(Opcode::Astore2),
            0x4e => Some(Opcode::Astore3),
            0xbf => Some(Opcode::Athrow),
            0x33 => Some(Opcode::Baload),
            0x54 => Some(Opcode::Bastore),
            0x10 => Some(Opcode::Bipush),
            0x34 => Some(Opcode::Caload),
            0x55 => Some(Opcode::Castore),
            0xc0 => Some(Opcode::Checkcast),
            0x90 => Some(Opcode::D2f),
            0x8e => Some(Opcode::D2i),
            0x8f => Some(Opcode::D2l),
            0x63 => Some(Opcode::Dadd),
            0x31 => Some(Opcode::Daload),
            0x52 => Some(Opcode::Dastore),
            0x98 => Some(Opcode::Dcmpg),
            0x97 => Some(Opcode::Dcmpl),
            0x0e => Some(Opcode::Dconst0),
            0x0f => Some(Opcode::Dconst1),
            0x6f => Some(Opcode::Ddiv),
            0x18 => Some(Opcode::Dload),
            0x26 => Some(Opcode::Dload0),
            0x27 => Some(Opcode::Dload1),
            0x28 => Some(Opcode::Dload2),
            0x29 => Some(Opcode::Dload3),
            0x6b => Some(Opcode::Dmul),
            0x77 => Some(Opcode::Dneg),
            0x73 => Some(Opcode::Drem),
            0xaf => Some(Opcode::Dreturn),
            0x39 => Some(Opcode::Dstore),
            0x47 => Some(Opcode::Dstore0),
            0x48 => Some(Opcode::Dstore1),
            0x49 => Some(Opcode::Dstore2),
            0x4a => Some(Opcode::Dstore3),
            0x67 => Some(Opcode::Dsub),
            0x59 => Some(Opcode::Dup),
            0x5a => Some(Opcode::DupX1),
            0x5b => Some(Opcode::DupX2),
            0x5c => Some(Opcode::Dup2),
            0x5d => Some(Opcode::Dup2X1),
            0x5e => Some(Opcode::Dup2X2),
            0x8d => Some(Opcode::F2d),
            0x8b => Some(Opcode::F2i),
            0x8c => Some(Opcode::F2l),
            0x62 => Some(Opcode::Fadd),
            0x30 => Some(Opcode::Faload),
            0x51 => Some(Opcode::Fastore),
            0x96 => Some(Opcode::Fcmpg),
            0x95 => Some(Opcode::Fcmpl),
            0x0b => Some(Opcode::Fconst0),
            0x0c => Some(Opcode::Fconst1),
            0x0d => Some(Opcode::Fconst2),
            0x6e => Some(Opcode::Fdiv),
            0x17 => Some(Opcode::Fload),
            0x22 => Some(Opcode::Fload0),
            0x23 => Some(Opcode::Fload1),
            0x24 => Some(Opcode::Fload2),
            0x25 => Some(Opcode::Fload3),
            0x6a => Some(Opcode::Fmul),
            0x76 => Some(Opcode::Fneg),
            0x72 => Some(Opcode::Frem),
            0xae => Some(Opcode::Freturn),
            0x38 => Some(Opcode::Fstore),
            0x43 => Some(Opcode::Fstore0),
            0x44 => Some(Opcode::Fstore1),
            0x45 => Some(Opcode::Fstore2),
            0x46 => Some(Opcode::Fstore3),
            0x66 => Some(Opcode::Fsub),
            0xb4 => Some(Opcode::Getfield),
            0xb2 => Some(Opcode::Getstatic),
            0xa7 => Some(Opcode::Goto),
            0xc8 => Some(Opcode::GotoW),
            0x91 => Some(Opcode::I2b),
            0x92 => Some(Opcode::I2c),
            0x87 => Some(Opcode::I2d),
            0x86 => Some(Opcode::I2f),
            0x85 => Some(Opcode::I2l),
            0x93 => Some(Opcode::I2s),
            0x60 => Some(Opcode::Iadd),
            0x2e => Some(Opcode::Iaload),
            0x7e => Some(Opcode::Iand),
            0x4f => Some(Opcode::Iastore),
            0x02 => Some(Opcode::IconstM1),
            0x03 => Some(Opcode::Iconst0),
            0x04 => Some(Opcode::Iconst1),
            0x05 => Some(Opcode::Iconst2),
            0x06 => Some(Opcode::Iconst3),
            0x07 => Some(Opcode::Iconst4),
            0x08 => Some(Opcode::Iconst5),
            0x6c => Some(Opcode::Idiv),
            0xa5 => Some(Opcode::IfAcmpeq),
            0xa6 => Some(Opcode::IfAcmpne),
            0x9f => Some(Opcode::IfIcmpeq),
            0xa0 => Some(Opcode::IfIcmpne),
            0xa1 => Some(Opcode::IfIcmplt),
            0xa2 => Some(Opcode::IfIcmpge),
            0xa3 => Some(Opcode::IfIcmpgt),
            0xa4 => Some(Opcode::IfIcmple),
            0x99 => Some(Opcode::Ifeq),
            0x9a => Some(Opcode::Ifne),
            0x9b => Some(Opcode::Iflt),
            0x9c => Some(Opcode::Ifge),
            0x9d => Some(Opcode:: Ifgt),
            0x9e => Some(Opcode::Ifle),
            0xc7 => Some(Opcode::Ifnonnull),
            0x84 => Some(Opcode::Iinc),
            0x15 => Some(Opcode::Iload),
            0x1a => Some(Opcode::Iload0),
            0x1b => Some(Opcode::Iload1),
            0x1c => Some(Opcode::Iload2),
            0x1d => Some(Opcode::Iload3),
            0x68 => Some(Opcode::Imul),
            0x74 => Some(Opcode::Ineg),
            0xc1 => Some(Opcode::Instanceof),
            0xba => Some(Opcode::Invokedynamic),
            0xb9 => Some(Opcode::Invokeinterface),
            0xb7 => Some(Opcode::Invokespecial),
            0xb8 => Some(Opcode::Invokestatic),
            0xb6 => Some(Opcode::Invokevirtual),
            0x80 => Some(Opcode::Ior),
            0x70 => Some(Opcode::Irem),
            0xac => Some(Opcode::Ireturn),
            0x78 => Some(Opcode::Ishl),
            0x7a => Some(Opcode::Ishr),
            0x36 => Some(Opcode::Istore),
            0x3b => Some(Opcode::Istore0),
            0x3c => Some(Opcode::Istore1),
            0x3d => Some(Opcode::Istore2),
            0x3e => Some(Opcode::Istore3),
            0x64 => Some(Opcode::Isub),
            0x7c => Some(Opcode::Iushr),
            0x82 => Some(Opcode::Ixor),
            0xa8 => Some(Opcode::Jsr),
            0xc9 => Some(Opcode::JsrW),
            0x8a => Some(Opcode::L2d),
            0x89 => Some(Opcode::L2f),
            0x88 => Some(Opcode::L2i),
            0x61 => Some(Opcode::Ladd),
            0x2f => Some(Opcode::Laload),
            0x7f => Some(Opcode::Land),
            0x50 => Some(Opcode::Lastore),
            0x94 => Some(Opcode::Lcmp),
            0x09 => Some(Opcode::Lconst0),
            0x0a => Some(Opcode::Lconst1),
            0x12 => Some(Opcode::Ldc),
            0x13 => Some(Opcode::LdcW),
            0x14 => Some(Opcode::Ldc2W),
            0x6d => Some(Opcode::Ldiv),
            0x16 => Some(Opcode::Lload),
            0x1e => Some(Opcode::Lload0),
            0x1f => Some(Opcode::Lload1),
            0x20 => Some(Opcode::Lload2),
            0x21 => Some(Opcode::Lload3),
            0x69 => Some(Opcode::Lmul),
            0x75 => Some(Opcode::Lneg),
            0xab => Some(Opcode::Lookupswitch),
            0x81 => Some(Opcode::Lor),
            0x71 => Some(Opcode::Lrem),
            0xad => Some(Opcode::Lreturn),
            0x79 => Some(Opcode::Lshl),
            0x7b => Some(Opcode::Lshr),
            0x37 => Some(Opcode::Lstore),
            0x3f => Some(Opcode::Lstore0),
            0x40 => Some(Opcode::Lstore1),
            0x41 => Some(Opcode::Lstore2),
            0x42 => Some(Opcode::Lstore3),
            0x65 => Some(Opcode::Lsub),
            0x7d => Some(Opcode::Lushr),
            0x83 => Some(Opcode::Lxor),
            0xc2 => Some(Opcode::Monitorenter),
            0xc3 => Some(Opcode::Monitorexit),
            0xc5 => Some(Opcode::Multianewarray),
            0xbb => Some(Opcode::New),
            0xbc => Some(Opcode::Newarray),
            0x00 => Some(Opcode::Nop),
            0x57 => Some(Opcode::Pop),
            0x58 => Some(Opcode::Pop2),
            0xb5 => Some(Opcode::Putfield),
            0xb3 => Some(Opcode::Putstatic),
            0xa9 => Some(Opcode::Ret),
            0xb1 => Some(Opcode::Return),
            0x35 => Some(Opcode::Saload),
            0x56 => Some(Opcode::Sastore),
            0x11 => Some(Opcode::Sipush),
            0x5f => Some(Opcode::Swap),
            0xaa => Some(Opcode::Tableswitch),
            0xc4 => Some(Opcode::Wide),
            _ => None
        }
    }

}

